minigym/envs/core/platformer.cp36-win32.pyd
minigym-0.2.0.dist-info/LICENSE
minigym-0.2.0.dist-info/METADATA
minigym-0.2.0.dist-info/WHEEL
minigym-0.2.0.dist-info/top_level.txt
minigym-0.2.0.dist-info/RECORD
