Metadata-Version: 2.1
Name: minigym
Version: 0.2.0
Summary: more gym environments
Home-page: https://github.com/cprogrammer1994/minigym
Author: Szabolcs Dombi
Author-email: cprogrammer1994@gmail.com
License: UNKNOWN
Platform: UNKNOWN
